CalibcheckUtils/__init__.py
CalibcheckUtils/calibcheckutils_gpu.py
CalibcheckUtils/config.py
CalibcheckUtils-0.0.2.dist-info/LICENSE
CalibcheckUtils-0.0.2.dist-info/METADATA
CalibcheckUtils-0.0.2.dist-info/WHEEL
CalibcheckUtils-0.0.2.dist-info/top_level.txt
CalibcheckUtils-0.0.2.dist-info/RECORD
